jupyter_annotator/__init__.py
jupyter_annotator/annotator.py
jupyter_annotator/utility.py
jupyter_annotator-1.0.0.dist-info/METADATA
jupyter_annotator-1.0.0.dist-info/WHEEL
jupyter_annotator-1.0.0.dist-info/top_level.txt
jupyter_annotator-1.0.0.dist-info/RECORD
