Metadata-Version: 2.1
Name: jupyter-annotator
Version: 1.0.0
Summary: This package provides an annotation UI for arbitrary dataset in json format.
Home-page: https://github.com/DoubleBite/jupyter-annotator
Author: Shih-hong Tsai
Author-email: doublebeet@gmail.com
License: UNKNOWN
Platform: UNKNOWN
Classifier: Programming Language :: Python :: 3
Classifier: License :: OSI Approved :: MIT License
Classifier: Operating System :: OS Independent
Requires-Python: >=3.7
